{
  "schemaVersion": 1,
  "taskId": "T03",
  "unitId": "M047/S02/T03",
  "timestamp": 1775028305054,
  "passed": true,
  "discoverySource": "task-plan",
  "checks": [
    {
      "command": "cargo test -p meshc --test e2e_m047_s02 -- --nocapture",
      "exitCode": 0,
      "durationMs": 9540,
      "verdict": "pass"
    },
    {
      "command": "cargo test -p meshc --test e2e_m046_s02 m046_s02_ -- --nocapture",
      "exitCode": 0,
      "durationMs": 13403,
      "verdict": "pass"
    }
  ]
}
