{
  "schemaVersion": 1,
  "taskId": "T04",
  "unitId": "M055/S05/T04",
  "timestamp": 1775590798508,
  "passed": false,
  "discoverySource": "task-plan",
  "checks": [
    {
      "command": "bash scripts/verify-m055-s04.sh",
      "exitCode": 127,
      "durationMs": 120227,
      "verdict": "fail"
    },
    {
      "command": "rg -n \"^verdict: pass$\" .gsd/milestones/M055/M055-VALIDATION.md",
      "exitCode": 0,
      "durationMs": 185,
      "verdict": "pass"
    }
  ],
  "retryAttempt": 1,
  "maxRetries": 2
}
